{
	"configurations" : 
	[
		{
			"directories" : 
			[
				{
					"build" : ".",
					"jsonFile" : "directory-.-Debug-f5ebdc15457944623624.json",
					"minimumCMakeVersion" : 
					{
						"string" : "3.26"
					},
					"projectIndex" : 0,
					"source" : ".",
					"targetIndexes" : 
					[
						0
					]
				}
			],
			"name" : "Debug",
			"projects" : 
			[
				{
					"directoryIndexes" : 
					[
						0
					],
					"name" : "progettoAPI_2023",
					"targetIndexes" : 
					[
						0
					]
				}
			],
			"targets" : 
			[
				{
					"directoryIndex" : 0,
					"id" : "progettoAPI_2023::@6890427a1f51a3e7e1df",
					"jsonFile" : "target-progettoAPI_2023-Debug-3ec37f233ed96dd19b5a.json",
					"name" : "progettoAPI_2023",
					"projectIndex" : 0
				}
			]
		}
	],
	"kind" : "codemodel",
	"paths" : 
	{
		"build" : "/home/ginny/Documenti/GitHub/progettoAPI_2023/cmake-build-debug",
		"source" : "/home/ginny/Documenti/GitHub/progettoAPI_2023"
	},
	"version" : 
	{
		"major" : 2,
		"minor" : 5
	}
}
